await_ccb.py
await_ccb/__init__.py
await_ccb/build_poller.py
await_ccb/cli.py
await_ccb-0.1.3.dist-info/METADATA
await_ccb-0.1.3.dist-info/RECORD
await_ccb-0.1.3.dist-info/WHEEL
await_ccb-0.1.3.dist-info/entry_points.txt
await_ccb-0.1.3.dist-info/top_level.txt
