Metadata-Version: 2.1
Name: await-ccb
Version: 0.1.3
Summary: Waits for Google Cloud Container Build to complete
Home-page: https://github.com/thedyrt/await-ccb
Author: Reid Beels
Author-email: reid@thedyrt.com
License: MIT
Keywords: google cloud container builder
Platform: UNKNOWN
Classifier: Development Status :: 3 - Alpha
Classifier: Intended Audience :: Developers
Classifier: Intended Audience :: System Administrators
Classifier: Topic :: Software Development :: Build Tools
Classifier: License :: OSI Approved :: MIT License
Classifier: Programming Language :: Python :: 2
Classifier: Programming Language :: Python :: 2.6
Classifier: Programming Language :: Python :: 2.7
Classifier: Programming Language :: Python :: 3
Classifier: Programming Language :: Python :: 3.2
Classifier: Programming Language :: Python :: 3.3
Classifier: Programming Language :: Python :: 3.4
Classifier: Programming Language :: Python :: 3.5
Classifier: Programming Language :: Python :: 3.6
Requires-Dist: google-auth
Requires-Dist: google-auth-httplib2
Requires-Dist: google-api-python-client
Requires-Dist: docopt
